chapter_by_chapter/__init__.py
chapter_by_chapter/bot.py
chapter_by_chapter/content_creator.py
chapter_by_chapter/greeter.py
chapter_by_chapter/models.py
chapter_by_chapter/processor.py
chapter_by_chapter/processors/__init__.py
chapter_by_chapter/processors/base_processor.py
chapter_by_chapter/processors/gutenberg/__init__.py
chapter_by_chapter/processors/gutenberg/gutenberg_html.py
chapter_by_chapter/processors/gutenberg/gutenberg_text.py
chapter_by_chapter/py.typed
chapter_by_chapter/resources/templates/about_author.txt
chapter_by_chapter/resources/templates/about_book.txt
chapter_by_chapter/resources/templates/book_ending/1.txt
chapter_by_chapter/resources/templates/book_ending/2.txt
chapter_by_chapter/resources/templates/book_ending/3.txt
chapter_by_chapter/resources/templates/book_intro/1.txt
chapter_by_chapter/resources/templates/book_intro/2.txt
chapter_by_chapter/resources/templates/book_intro/3.txt
chapter_by_chapter/resources/templates/book_intro_link.txt
chapter_by_chapter/resources/templates/book_metadata.json
chapter_by_chapter/resources/templates/chapter_spoiler.txt
chapter_by_chapter/resources/templates/chapter_text.txt
chapter_by_chapter/resources/templates/daily_ending.txt
chapter_by_chapter/resources/templates/daily_intro/1.txt
chapter_by_chapter/resources/templates/daily_intro/2.txt
chapter_by_chapter/resources/templates/daily_intro/3.txt
chapter_by_chapter/resources/word_choices.json
chapter_by_chapter/stubs/chapter_by_chapter/__init__.pyi
chapter_by_chapter/stubs/chapter_by_chapter/bot.pyi
chapter_by_chapter/stubs/chapter_by_chapter/content_creator.pyi
chapter_by_chapter/stubs/chapter_by_chapter/greeter.pyi
chapter_by_chapter/stubs/chapter_by_chapter/models.pyi
chapter_by_chapter/stubs/chapter_by_chapter/processor.pyi
chapter_by_chapter/stubs/chapter_by_chapter/processors/__init__.pyi
chapter_by_chapter/stubs/chapter_by_chapter/processors/base_processor.pyi
chapter_by_chapter/stubs/chapter_by_chapter/processors/gutenberg/__init__.pyi
chapter_by_chapter-0.2.0.dist-info/LICENSE
chapter_by_chapter-0.2.0.dist-info/METADATA
chapter_by_chapter-0.2.0.dist-info/WHEEL
chapter_by_chapter-0.2.0.dist-info/RECORD
