Metadata-Version: 2.1
Name: chapter-by-chapter
Version: 0.2.0
Summary: Serializes classic literature to Mastodon
Home-page: https://codeberg.org/bfordham/chapter-by-chapter
License: AGPL 3.0
Keywords: mastodon,bot,social-media,markov,automation
Author: Bryan L. Fordham
Author-email: bfordham@naughtybaptist.com
Requires-Python: >=3.12,<4.0
Classifier: Development Status :: 4 - Beta
Classifier: Intended Audience :: Developers
Classifier: License :: OSI Approved :: GNU Affero General Public License v3
Classifier: License :: Other/Proprietary License
Classifier: Operating System :: OS Independent
Classifier: Programming Language :: Python :: 3
Classifier: Programming Language :: Python :: 3.12
Classifier: Topic :: Communications :: Chat
Classifier: Topic :: Internet :: WWW/HTTP :: Dynamic Content
Classifier: Topic :: Software Development :: Libraries :: Python Modules
Classifier: Typing :: Typed
Requires-Dist: beautifulsoup4 (>=4.13.4,<5.0.0)
Requires-Dist: robotooter (>=0.3.0,<0.4.0)
Project-URL: Documentation, https://codeberg.org/bfordham/chapter-by-chapter#readme
Project-URL: Repository, https://codeberg.org/bfordham/chapter-by-chapter
